proton_mail_export_organizer.py
proton_mail_export_organizer-0.4.dist-info/entry_points.txt
proton_mail_export_organizer-0.4.dist-info/LICENSE
proton_mail_export_organizer-0.4.dist-info/WHEEL
proton_mail_export_organizer-0.4.dist-info/METADATA
proton_mail_export_organizer-0.4.dist-info/RECORD
