Metadata-Version: 2.1
Name: proton_mail_export_organizer
Version: 0.4
Summary: Tool to sort emails from a proton-mail-export directory into folders.
Author-email: Julien Palard <julien@palard.fr>
Classifier: License :: OSI Approved :: MIT License
Project-URL: Home, https://git.afpy.org/mdk/proton-mail-export-organizer
